chaossaltstack/__init__.py
chaossaltstack/machine/__init__.py
chaossaltstack/machine/actions.py
chaossaltstack/machine/constants.py
chaossaltstack/machine/probes.py
chaossaltstack/machine/scripts/burn_io.sh
chaossaltstack/machine/scripts/cpu_stress_test.ps1
chaossaltstack/machine/scripts/cpu_stress_test.sh
chaossaltstack/machine/scripts/fill_disk.ps1
chaossaltstack/machine/scripts/fill_disk.sh
chaossaltstack/machine/scripts/network_advanced.sh
chaossaltstack/machine/scripts/network_latency.sh
chaostoolkit_saltstack-0.1.0.dist-info/LICENSE
chaostoolkit_saltstack-0.1.0.dist-info/METADATA
chaostoolkit_saltstack-0.1.0.dist-info/WHEEL
chaostoolkit_saltstack-0.1.0.dist-info/top_level.txt
chaostoolkit_saltstack-0.1.0.dist-info/RECORD
